dabom_langchain/__init__.py
dabom_langchain/dabom_search.py
dabom_langchain/dabom_search_api_wrapper.py
dabom_langchain-0.1.5.dist-info/LICENCE
dabom_langchain-0.1.5.dist-info/METADATA
dabom_langchain-0.1.5.dist-info/WHEEL
dabom_langchain-0.1.5.dist-info/top_level.txt
dabom_langchain-0.1.5.dist-info/RECORD
