Metadata-Version: 2.1
Name: dabom-langchain
Version: 0.1.5
Summary: Langchain extension for Dabom Search API
Author-email: Dongho Yee <dongho3929@gmail.com>
Project-URL: Homepage, https://github.com/LighterLinks/dabom-langchain.git
Classifier: Programming Language :: Python :: 3
Classifier: License :: OSI Approved :: MIT License
Classifier: Operating System :: OS Independent
Requires-Python: >=3.8
License-File: LICENCE
Requires-Dist: langchain
Requires-Dist: aiohttp
